minimal_cernsso/__init__.py
minimal_cernsso-0.0.2.dist-info/entry_points.txt
minimal_cernsso-0.0.2.dist-info/WHEEL
minimal_cernsso-0.0.2.dist-info/METADATA
minimal_cernsso-0.0.2.dist-info/RECORD
