Metadata-Version: 2.1
Name: minimal-cernsso
Version: 0.0.2
Summary: Minimal implementation of getting a CERN SSO cookie
Author: Thomas Klijnsma
Author-email: tklijnsm@gmail.com
Requires-Python: >=2.7, !=3.0.*, !=3.1.*, !=3.2.*, !=3.3.*, !=3.4.*, !=3.5.*
Classifier: Programming Language :: Python :: 2
Classifier: Programming Language :: Python :: 2.7
Classifier: Programming Language :: Python :: 3
Classifier: Programming Language :: Python :: 3.6
Classifier: Programming Language :: Python :: 3.7
Classifier: Programming Language :: Python :: 3.8
Classifier: Programming Language :: Python :: 3.9
Requires-Dist: requests (>=2,<3)
Requires-Dist: six (>=1.15,<2.0)
